{
  "name": "TypePlat",
  "fields": [
    {
      "fieldName": "type",
      "fieldType": "String"
    },
    {
      "fieldName": "imagePath",
      "fieldType": "byte[]",
      "fieldTypeBlobContent": "text"
    }
  ],
  "relationships": [
    {
      "relationshipType": "one-to-many",
      "otherEntityName": "plat",
      "otherEntityRelationshipName": "typePlat",
      "relationshipName": "plat"
    }
  ],
  "entityTableName": "type_plat",
  "dto": "mapstruct",
  "pagination": "pagination",
  "service": "serviceImpl",
  "jpaMetamodelFiltering": true,
  "fluentMethods": true,
  "readOnly": false,
  "embedded": false,
  "applications": "*",
  "changelogDate": "20220527094039"
}
